linien_influxdb/__init__.py
linien_influxdb/app.py
linien_influxdb/example_config.ini
linien_influxdb-2.0.3.dist-info/LICENSE
linien_influxdb-2.0.3.dist-info/METADATA
linien_influxdb-2.0.3.dist-info/WHEEL
linien_influxdb-2.0.3.dist-info/entry_points.txt
linien_influxdb-2.0.3.dist-info/top_level.txt
linien_influxdb-2.0.3.dist-info/RECORD
