Metadata-Version: 2.1
Name: linien-influxdb
Version: 2.0.3
Summary: Log status of linien locking application to influxdb
Author: Bastian Leykauf
Author-email: leykauf@physik.hu-berlin.de
License: GNU GENERAL PUBLIC LICENSE
Project-URL: homepage, https://github.com/linien-org/linien-influxdb/
Project-URL: repository, https://github.com/linien-org/linien-influxdb/
Classifier: Programming Language :: Python :: 3
Classifier: License :: OSI Approved :: GNU General Public License v3 (GPLv3)
Classifier: Operating System :: OS Independent
Requires-Python: >=3.7
License-File: LICENSE
Requires-Dist: influxdb-client (>=1.27.0)
Requires-Dist: configparser (>=5.2.0)
Requires-Dist: click (>=8.1.2)
Requires-Dist: linien-python-client (>=^0.5.3)
Provides-Extra: dev
Requires-Dist: black (>=22.8.0) ; extra == 'dev'
Requires-Dist: pre-commit (>=2.20.0) ; extra == 'dev'
Requires-Dist: flake8 (>=5.0.4) ; extra == 'dev'
Requires-Dist: rope (>=1.3.0) ; extra == 'dev'
Requires-Dist: isort (>=5.10.1) ; extra == 'dev'
Requires-Dist: Flake8-pyproject (>=1.1.0.post0) ; extra == 'dev'
Requires-Dist: setuptools-scm (>=6.2) ; extra == 'dev'
